Metadata-Version: 1.1
Name: ColdsoberClock
Version: 0.0.1
Summary: GUI clock for tkinter based projects
Home-page: UNKNOWN
Author: coldsober irene
Author-email: nseirene3@gmail.com
License: MIT
Keywords: clock,time,date,datetime
Platform: UNKNOWN
Classifier: Development Status :: 5 - Production/Stable
Classifier: Intended Audience :: Education
Classifier: Operating System :: Microsoft :: Windows :: Windows 10
Classifier: License :: OSI Approved :: MIT License
Classifier: Programming Language :: Python :: 3
